my_bezeq/__init__.py
my_bezeq/api.py
my_bezeq/api_state.py
my_bezeq/auth_api.py
my_bezeq/commons.py
my_bezeq/const.py
my_bezeq/dashboard_api.py
my_bezeq/electric_api.py
my_bezeq/exceptions.py
my_bezeq/generic_actions_api.py
my_bezeq/internet_api.py
my_bezeq/invoices_api.py
my_bezeq/models/base.py
my_bezeq/models/call_log.py
my_bezeq/models/card_data.py
my_bezeq/models/cards.py
my_bezeq/models/common.py
my_bezeq/models/customer_messages.py
my_bezeq/models/dashboard.py
my_bezeq/models/electric_invoice.py
my_bezeq/models/electric_report.py
my_bezeq/models/electricity_tab.py
my_bezeq/models/extender_details.py
my_bezeq/models/feeds.py
my_bezeq/models/glassix_token.py
my_bezeq/models/internet_tab.py
my_bezeq/models/invoice.py
my_bezeq/models/menu.py
my_bezeq/models/personal.py
my_bezeq/models/phone.py
my_bezeq/models/registered_devices.py
my_bezeq/models/site_config.py
my_bezeq/models/sms.py
my_bezeq/models/speed_test_card.py
my_bezeq/models/start_actions.py
my_bezeq/models/time_windows.py
my_bezeq/models/username_login.py
my_bezeq/models/wifi_data.py
my_bezeq/personal_api.py
my_bezeq/phone_api.py
my_bezeq/tech_coord_api.py
py_my_bezeq-0.1.5.dist-info/LICENSE
py_my_bezeq-0.1.5.dist-info/METADATA
py_my_bezeq-0.1.5.dist-info/WHEEL
py_my_bezeq-0.1.5.dist-info/RECORD
